pypruningradixtrie/entry.py
pypruningradixtrie/input/abstract_input_provider.py
pypruningradixtrie/input/csv_input_provider.py
pypruningradixtrie/input/input.py
pypruningradixtrie/input/json_input_provider.py
pypruningradixtrie/insert.py
pypruningradixtrie/trie.py
pypruningradixtrie/trie_node.py
pypruningradixtrie-2.1.0.dist-info/WHEEL
pypruningradixtrie-2.1.0.dist-info/METADATA
pypruningradixtrie-2.1.0.dist-info/RECORD
