Metadata-Version: 2.1
Name: pypruningradixtrie
Version: 2.1.0
Summary: Radix trie for fast prefix search.
Home-page: https://github.com/otto-de/PyPruningRadixTrie
License: MIT
Author: tomglk
Requires-Python: >=3.7,<4.0
Classifier: License :: OSI Approved :: MIT License
Classifier: Programming Language :: Python :: 3
Classifier: Programming Language :: Python :: 3.7
Classifier: Programming Language :: Python :: 3.8
Classifier: Programming Language :: Python :: 3.9
Classifier: Programming Language :: Python :: 3.10
Classifier: Programming Language :: Python :: 3.11
Project-URL: Repository, https://github.com/otto-de/PyPruningRadixTrie
